threadspy/__init__.py
threadspy/auth.py
threadspy/client.py
threadspy/constants.py
threadspy/models.py
threadspy/utils.py
threads_py_wrapper-0.0.2.dist-info/LICENSE
threads_py_wrapper-0.0.2.dist-info/METADATA
threads_py_wrapper-0.0.2.dist-info/WHEEL
threads_py_wrapper-0.0.2.dist-info/top_level.txt
threads_py_wrapper-0.0.2.dist-info/RECORD
