Metadata-Version: 2.1
Name: threads-py-wrapper
Version: 0.0.2
Summary: Unofficial API for Threads by Instagram. With type hints.
Home-page: https://github.com/yash-dk/threads.py
Author: Yash Khadse
License: MIT
Project-URL: Issue Tracker, https://github.com/yash-dk/threads.py/issues
Project-URL: Source Code, https://github.com/yash-dk/threads.py
Project-URL: Download, https://github.com/yash-dk/threads.py/tags
Classifier: Operating System :: OS Independent
Classifier: Intended Audience :: Developers
Classifier: License :: OSI Approved :: MIT License
Classifier: Programming Language :: Python :: 3.8
Classifier: Programming Language :: Python :: 3.9
Classifier: Programming Language :: Python :: 3.10
Classifier: Programming Language :: Python :: 3.11
License-File: LICENSE
Requires-Dist: cryptography (>=41.0.2)
Requires-Dist: instagrapi (>=1.17.13)
